pynenguk_quiz/__init__.py
pynenguk_quiz/help_table_widget.py
pynenguk_quiz/question_table_widget.py
pynenguk_quiz/questions.json
pynenguk_quiz/select_questions_widget.py
pynenguk_quiz/termquiz.py
pynenguk_quiz-0.7.3.dist-info/licenses/LICENSE
pynenguk_quiz-0.7.3.dist-info/METADATA
pynenguk_quiz-0.7.3.dist-info/WHEEL
pynenguk_quiz-0.7.3.dist-info/entry_points.txt
pynenguk_quiz-0.7.3.dist-info/top_level.txt
pynenguk_quiz-0.7.3.dist-info/RECORD
